rfb_cycler_db_sync/__init__.py
rfb_cycler_db_sync/__version__.py
rfb_cycler_db_sync/context.py
rfb_cycler_db_sync/db_sync_fachade.py
rfb_cycler_db_sync/db_sync_node.py
rfb_cycler_db_sync-0.0.1.dist-info/LICENSE.txt
rfb_cycler_db_sync-0.0.1.dist-info/METADATA
rfb_cycler_db_sync-0.0.1.dist-info/WHEEL
rfb_cycler_db_sync-0.0.1.dist-info/top_level.txt
rfb_cycler_db_sync-0.0.1.dist-info/RECORD
